{"titleEn":"Charming Person","slug":"pang-nakarin-kon-mee-sanay","titleTh":"คนมีเสน่ห์","titleRo":"Kon Mee Sanay","duration":"319","url":"R10mrTJpqPw","releaseYear":2016,"type":"Single","label":{"metadata":{"tags":[]},"sys":{"space":{"sys":{"type":"Link","linkType":"Space","id":"exl0x88tcld8"}},"id":"3nLlOILZmdsSYrjVNkadoV","type":"Entry","createdAt":"2020-05-16T08:56:24.946Z","updatedAt":"2020-05-16T08:56:24.946Z","environment":{"sys":{"id":"master","type":"Link","linkType":"Environment"}},"revision":1,"contentType":{"sys":{"type":"Link","linkType":"ContentType","id":"labels"}},"locale":"en-US"},"fields":{"name":"Genie Rock","slug":"genie-rock"}},"artists":[{"metadata":{"tags":[]},"sys":{"space":{"sys":{"type":"Link","linkType":"Space","id":"exl0x88tcld8"}},"id":"2qLOPq5NLKDuk3Yv90abXr","type":"Entry","createdAt":"2020-05-02T10:40:42.298Z","updatedAt":"2020-06-30T08:52:05.975Z","environment":{"sys":{"id":"master","type":"Link","linkType":"Environment"}},"revision":2,"contentType":{"sys":{"type":"Link","linkType":"ContentType","id":"artists"}},"locale":"en-US"},"fields":{"name":"Pang Nakarin","slug":"pang-nakarin","avatar":{"metadata":{"tags":[]},"sys":{"space":{"sys":{"type":"Link","linkType":"Space","id":"exl0x88tcld8"}},"id":"41faWbKsnKtxdyGnaHyUGg","type":"Asset","createdAt":"2020-05-02T10:36:15.399Z","updatedAt":"2020-05-02T10:36:15.399Z","environment":{"sys":{"id":"master","type":"Link","linkType":"Environment"}},"revision":1,"locale":"en-US"},"fields":{"title":"pang-nakarin-avatar-00","file":{"url":"//images.ctfassets.net/exl0x88tcld8/41faWbKsnKtxdyGnaHyUGg/e6956992d1cb1677dcfc3ae539df873f/c7350fa6073dde9b41dfefe17f6352c5be65186f","details":{"size":144542,"image":{"width":640,"height":640}},"fileName":"c7350fa6073dde9b41dfefe17f6352c5be65186f","contentType":"image/jpeg"}}},"biography":{"data":{},"content":[{"data":{},"content":[{"data":{},"marks":[],"value":"Giới thiệu về Pang Nakarin\nCa sĩ và nhạc sĩ âm nhạc thế giới nổi tiếng với các bài hát \"Kon Mee Sanay\", \"Auem Mai Tueng, \"và\" Phuchai Ronghai. \" Anh ấy đã tiếp tục thu hút hơn 30.000 người theo dõi trên tài khoản Instagram cùng tên của mình.","nodeType":"text"}],"nodeType":"paragraph"},{"data":{},"content":[{"data":{},"marks":[],"value":"Trước khi nổi tiếng\nKhi anh ấy 12 tuổi, anh ấy bắt đầu sử dụng hộp các tông và gối làm trống.","nodeType":"text"}],"nodeType":"paragraph"},{"data":{},"content":[{"data":{},"marks":[],"value":"Thành tích\nAnh ấy đã gián đoạn hai năm từ âm nhạc từ năm 2014 đến 2016.","nodeType":"text"}],"nodeType":"paragraph"},{"data":{},"content":[{"data":{},"marks":[],"value":"Cuộc sống gia đình\nAnh ấy cưới vợ Anutra Kingsak vào năm 1999. Cặp vợ chồng có một đứa con tên là Kamin Kingsak.","nodeType":"text"}],"nodeType":"paragraph"},{"data":{},"content":[{"data":{},"marks":[],"value":"Hiệp hội\nCả anh và người biểu diễn âm nhạc thế giới đồng nghiệp Cnan Kamikaze được sinh ra ở Thái Lan.","nodeType":"text"}],"nodeType":"paragraph"}],"nodeType":"document"},"birthday":"1967-02-24","isBand":false}}],"lyricsTh":"เฮ เธอ ทำไมตัวเธอถึงด๊ำดำ\nHey tur tummai dtua tur teung dum dum\nHey, you, why are you so black?\nโอ้แม่งามขำ ดำเป็นดินสอขนาด 2B\nOh mae ngahm kum dum bpen din sor kanaht 2B\nOh, pretty mama, you’re as black as a 2B pencil\nหน้าอกหน้าใจ ก็ดูเหมือนจะไม่มี\nNah auk nah jai gor doo meuan ja mai mee\nIt seems like you don’t have breasts\nจอแบนอย่างนี้ หมอเกาหลีคงไม่รับทำ\nJor baen yahng nee mor gaolee kong mai rup tum\nAs flat-chested as this, Korean plastic surgeons probably would refuse to take you\n\nท่อนแขนก็จัดว่าใหญ่ ผู้หญิงอะไรขาโต\nTaun kaen gor jut wah yai poo ying arai kah dtoh\nYour arms are huge, what woman has such thick legs?\nใครทำให้เธอโมโห ต้องคอหักตาย\nKrai tum hai tur moh hoh dtaun gkor huk dtai\nEveryone who pisses you off gets their neck broken\nไม่รู้น้ำหนักเท่าไร กล้าชั่งให้ดูไหมนี่\nMai roo num nuk tao rai glah chung hai doo mai nee\nI don’t know how much you weigh, would you be brave enough to weigh yourself and show me?\nถ้าเอาเธอมาแยกมองแต่ละที่ ไม่เห็นจะมีอะไรสวยเลย\nTah ao tur mah yaek maung dtae la tee mai hen ja mee arai suay loey\nIf I split you up and looked at each individual part, it doesn’t seem like anything is beautiful\n\n(*) (แต่)(พอ)ดูรวมๆ แล้วมีเสน่ห์เหลือเกิน\n(Dtae) (Por) doo ruam ruam laeo mee sanay leua gern\n(But) (As soon as) I look at everything together, you’re so charming\nไม่ต้องมาเขิน ฉันพูดจริงๆ\nMai dtaung mah kern chun poot jing jing\nThere’s no need to be shy, I’m telling the truth\nเธอมีเสน่ห์มากมาย จะน่ารักไปไหน\nTur mee sanay mahk mai ja naruk bpai nai\nYou have a lot of charm, why are you so cute?\nอยากจะได้แอบอิง ยิ่งดูยิ่งมีเสน่ห์\nYahk ja dai aep ing ying doo ying mee sanay\nI want to snuggle up to you, the more I look, the more charming you are\n\nเฮ เธอ ที่ฉันปากเสียเสมอมา\nHey tur tee chun bpahk sia samur mah\nHey, you, whom I’m always insulting\nรู้ไว้เถอะหนา เพียงเรียกร้องให้เธอสนใจ\nRoo wai tur nah piang riak raung hai tur son jai\nKeep in mind that I’m only calling you out to make you pay attention\nก็ไม่รู้จะเริ่มจีบโดยคำพูดใด\nGor mai roo ja rerm jeep doy kum poot dai\nI don’t know what words to start flirting with\nที่ล้อเลียนไป จริงๆแล้วมันคลั่งไคล้เธอ\nTee lor lian bpai jing jing laeo mun klung klai tur\nI’m mocking you really because I’m crazy about you\n\nน่ารักตอนเธอพูดจา ลึกซึ้งถ้าเป็นเรื่องใจ\nNaruk dtaun tur poot jahk leuk seung tah bpen reuang jai\nYou’re cute when you speak, it’s touching if it’s from the heart\nเธอมองอะไร อะไร ด้วยความอ่อนโยน\nTur maung arai arai duay kwahm aun yohn\nYou look at everything with gentleness\nไม่สมบูรณ์แต่สมดุล เห็นภาพรวมเธอแล้วโดน\nMai somboon dtae somdoon hen pahp ruam tur laeo dohn\nYou’re imperfect yet balanced, seeing your overall image, I’ve been struck\nรู้ไหมใจฉันดวงนี้มันสับสน หลงใหลเธอจนหมดใจแล้วเอย﻿\nRoo mai jai chun duang nee mun sup son long lai tur jon mot jai laeo oey\nDo you know that this heart of mine is feeling mixed up? I’ve become entranced by you with all my heart\n\n(*)\n\nมันทำไม มันทำไม\nMun tummai mun tummai\nWhy? Why?\n\nมันทำไม ด๊ำดำ ทำไม แบ๊นแบน\nMun tummai dum dum tummai baen baen\nWhy are you so black? Why are you flat-chested?\nทำไมแขนใหญ่ คนอะไรขาโต ( X 3 )\nTummai kaen yai kon arai kah dtoh\nWhy are your arms huge? What person has such thick legs?\n\nมันทำไม มันทำไม มันทำไม มันทำไม\nMun tummai mun tummai mun tummai mun tummai\nWhy? Why? Why? Why?\nแล้วทำไม แล้วทำไม\nLaeo tummai laeo tummai\nSo why? So why?\n\n(*)\n\nยิ่งดูยิ่งมีเสน่ห์\nYing doo ying mee sanay\nThe more I look, the more charming you are","deungdutjaisNote":"What a cute, teasingly loving song by the great Pang Nakarin~ At first listen, I was a little shocked, like why you gotta be so mean?? But the more I listened to it, the more teasingly sweet it became, as it’s reminding us that it’s usually someone’s imperfections that attract us to them. I like the direction the music video took it in, with everyone else teasing the poor girl about her appearance while the guy watches her fondly, but seriously, I have had it with music videos that have an “ugly” girl who magically becomes hot when she takes off her glasses. She was never ugly, come on haha.","likeCount":720933,"viewCount":304484087,"dislikeCount":52449,"publishDate":"2016-06-21T13:00:11Z","similars":[{"url":"T_4RvW2zFww","slug":"labanoon-pae-tahng","titleEn":"My Weakness","titleRo":"Pae Tahng","titleTh":"แพ้ทาง","duration":"242","likeCount":778555,"viewCount":392630408,"artistsIds":["4u8Anx3ujtOJSreNa191K7"],"publishDate":"2016-02-10T12:59:28Z","dislikeCount":56434},{"url":"dr-5SO5HgQY","slug":"pang-nakarin-poom-pae-krungthep","titleEn":"Allergic To Bangkok","titleRo":"Poom Pae Krungthep","titleTh":"ภูมิแพ้กรุงเทพ","duration":"433","likeCount":469291,"viewCount":182829167,"artistsIds":["2qLOPq5NLKDuk3Yv90abXr"],"publishDate":"2013-09-02T12:03:30Z","dislikeCount":40066},{"url":"QyhrOruvT1c","slug":"atom-aw","titleEn":"Oh","titleRo":"Aw","titleTh":"อ้าว","duration":"344","likeCount":428512,"viewCount":196701796,"artistsIds":["1csURFGgST9x9EfzEuRoY7"],"publishDate":"2016-08-09T13:02:08Z","dislikeCount":20444},{"url":"wqJsZYibWcI","slug":"palmy-saun-glin","titleEn":"Tuberose","titleRo":"Saun Glin","titleTh":"ซ่อนกลิ่น","duration":"314","likeCount":568396,"viewCount":124413231,"artistsIds":["XWvb1ogRWHyZvKdSeATC8"],"publishDate":"2018-10-19T11:00:01Z","dislikeCount":24524},{"url":"c8gPY2CZqC4","slug":"pang-nakarin-took-kon-koey-raung-hai","titleEn":"Everyone Has Cried Before","titleRo":"Took Kon Koey Raung Hai","titleTh":"ทุกคนเคยร้องไห้","duration":"417","likeCount":591705,"viewCount":195793335,"artistsIds":["2qLOPq5NLKDuk3Yv90abXr"],"publishDate":"2017-09-01T13:00:22Z","dislikeCount":59367},{"url":"GjnC-KKKU2E","slug":"pang-nakarin-gum","titleEn":"Sin","titleRo":"Gum","titleTh":"กรรม","duration":"280","likeCount":824565,"viewCount":240494873,"artistsIds":["2qLOPq5NLKDuk3Yv90abXr"],"publishDate":"2019-06-06T11:00:05Z","dislikeCount":43594}],"lastUpdatedSimilars":"2020-07-03T08:27:10.457Z"}